rclip/const.py
rclip/db.py
rclip/fs.py
rclip/main.py
rclip/model.py
rclip/utils/helpers.py
rclip/utils/preview.py
rclip/utils/snap.py
rclip-2.0.11.dist-info/METADATA
rclip-2.0.11.dist-info/WHEEL
rclip-2.0.11.dist-info/entry_points.txt
rclip-2.0.11.dist-info/licenses/LICENSE
rclip-2.0.11.dist-info/RECORD
