Metadata-Version: 2.4
Name: rclip
Version: 2.0.11
Summary: AI-Powered Command-Line Photo Search Tool
License: MIT
License-File: LICENSE
Keywords: image search,computer vision,photography
Author: Yurij Mikhalevich
Author-email: yurij@mikhalevi.ch
Requires-Python: >=3.10,<3.13
Classifier: Intended Audience :: End Users/Desktop
Classifier: Intended Audience :: Science/Research
Classifier: License :: OSI Approved :: MIT License
Classifier: Programming Language :: Python :: 3
Classifier: Programming Language :: Python :: 3.10
Classifier: Programming Language :: Python :: 3.11
Classifier: Programming Language :: Python :: 3.12
Classifier: Topic :: Multimedia :: Graphics
Classifier: Topic :: Scientific/Engineering :: Artificial Intelligence
Classifier: Topic :: Scientific/Engineering :: Image Processing
Classifier: Topic :: Scientific/Engineering :: Image Recognition
Classifier: Topic :: Utilities
Requires-Dist: numpy (>=2.1.3,<2.2.0)
Requires-Dist: open_clip_torch (>=3.1.0,<4.0.0)
Requires-Dist: pillow (>=10.3.0,<11.0.0)
Requires-Dist: rawpy (>=0.24.0,<0.25.0)
Requires-Dist: requests (>=2.32,<3.0)
Requires-Dist: torch (==2.5.1) ; sys_platform != "linux" or platform_machine == "aarch64"
Requires-Dist: torch (==2.5.1+cpu) ; sys_platform == "linux" and platform_machine != "aarch64"
Requires-Dist: torchvision (==0.20.1) ; sys_platform != "linux" or platform_machine == "aarch64"
Requires-Dist: torchvision (==0.20.1+cpu) ; sys_platform == "linux" and platform_machine != "aarch64"
Requires-Dist: tqdm (>=4.65.0,<5.0.0)
Project-URL: Repository, https://github.com/yurijmikhalevich/rclip
